{"name":"User logs in and performs various actions","id":"user-registration;user-logs-in-and-performs-various-actions","testSteps":[{"number":1,"description":"Given I am on the login page","duration":8,"startTime":"2025-02-14T12:56:29.702-05:00[America/Bogota]","result":"PENDING","precondition":false,"level":0},{"number":2,"description":"When I log in with valid credentials","duration":10,"startTime":"2025-02-14T12:56:29.712-05:00[America/Bogota]","result":"IGNORED","precondition":false,"level":0},{"number":3,"description":"Then I should be successfully logged in","duration":10,"startTime":"2025-02-14T12:56:29.725-05:00[America/Bogota]","result":"IGNORED","precondition":false,"level":0}],"userStory":{"id":"user-registration","storyName":"User Registration","displayName":"User Registration","path":"yourStoreWeb.feature","type":"feature","qualifiedTag":{"name":"User Registration","type":"feature","displayName":"User Registration"}},"featureTag":{"name":"User Registration","type":"feature","displayName":"User Registration"},"title":"User logs in and performs various actions","description":"","tags":[{"name":"User Registration","type":"feature","displayName":"User Registration"}],"allTags":[{"name":"User Registration","type":"feature","displayName":"User Registration"}],"startTime":"2025-02-14T12:56:29.680-05:00[America/Bogota]","duration":58,"projectKey":"","annotatedResult":"PENDING","isManualTestingUpToDate":false,"context":"windows","manual":false,"testSource":"Cucumber","result":"PENDING"}